gseda/__init__.py
gseda/16s/analysis.py
gseda/16s/vcf_position_distribution.py
gseda/aligned_bam_ana/long_ins_cnt.py
gseda/aligned_bam_ana/low_window_identity.py
gseda/aligned_bam_ana/range_identity.py
gseda/alignment/edlib_align.py
gseda/alignment_result_ana/channel_level_ana.py
gseda/bam_ana/avg_passes.py
gseda/bam_ana/bam_basic_stat.py
gseda/bam_ana/bam_channel_extractor.py
gseda/bam_ana/high_base_q_ana.py
gseda/bam_ana/hpc_ana.py
gseda/bam_ana/length_scatter.py
gseda/bam_ana/mem_est.py
gseda/bam_checker/__init__.py
gseda/bam_checker/subreads_bam_checker.py
gseda/bam_filter/__init__.py
gseda/bam_filter/bam2fx.py
gseda/bam_filter/drop_multiple_mapping_reads.py
gseda/bam_filter/dump_bam_subset.py
gseda/bam_filter/dump_smc_bam_subset.py
gseda/bam_filter/dump_smc_sub_bam.py
gseda/bam_filter/dump_smc_sub_bam_through_channels.py
gseda/bam_filter/dump_valid_bam.py
gseda/bam_surgery/__init__.py
gseda/bam_surgery/bam_hpc.py
gseda/bam_surgery/bam_partitioner.py
gseda/bam_surgery/called_bam2adapter_bam_directly.py
gseda/bam_surgery/dump_bam_subset_with_channel.py
gseda/bam_surgery/dump_sbr_bam_subset.py
gseda/bam_surgery/dump_single_seq_from_stranded_result.py
gseda/bam_surgery/first_n_channel_subreads.py
gseda/bam_surgery/generate_sbrbam.py
gseda/bam_surgery/insert_cs_to_sbr_bam.py
gseda/bam_surgery/insert_ref_to_sbr_bam.py
gseda/bam_surgery/merge_partitioned_adaptered_bam.py
gseda/eda_scripts/hp_data_analysis.py
gseda/fact_table_ana/__init__.py
gseda/fact_table_ana/ana_poly.py
gseda/fact_table_ana/polars_init.py
gseda/fact_table_ana/pred_baseq_and_emp_q.py
gseda/fact_table_ana/query_error_locus_ana.py
gseda/fact_table_ana/ref_locus_ana.py
gseda/fact_table_ana/rq_iy_analysis.py
gseda/fact_table_ana/subreads_discrepency_ana.py
gseda/fact_table_ana/utils.py
gseda/fastx_ana/fastx_basic_stat.py
gseda/file_format_cvt/bam2fastx.py
gseda/fx_filter/extract_ref_seq.py
gseda/fx_filter/filter_q_seq.py
gseda/msa_view/__init__.py
gseda/msa_view/msa_view.py
gseda-1.18.0.dist-info/METADATA
gseda-1.18.0.dist-info/WHEEL
gseda-1.18.0.dist-info/entry_points.txt
gseda-1.18.0.dist-info/RECORD
