Metadata-Version: 2.4
Name: gseda
Version: 1.18.0
Summary: gsetl
Project-URL: Homepage, https://github.com/keithyin/gsda
Project-URL: Issues, https://github.com/keithyin/gsda/issues
Author-email: keithyin <yinpenghhz@hotmail.com>
Classifier: License :: OSI Approved :: MIT License
Classifier: Operating System :: OS Independent
Classifier: Programming Language :: Python :: 3
Requires-Python: >=3.8
Requires-Dist: mappy
Requires-Dist: numba==0.58.0
Requires-Dist: numpy==1.24.4
Requires-Dist: polars==1.8.2
Requires-Dist: pyarrow==17.0.0
Requires-Dist: pymsaviz==0.4.2
Requires-Dist: pysam>=0.22
Requires-Dist: seaborn>=0.13
Requires-Dist: semver==3.0.2
Requires-Dist: tqdm>=4.67
